ws_scoring/__init__.py
ws_scoring/module_ws_scoring.py
django_ws_scoring-0.2.1.dist-info/LICENSE
django_ws_scoring-0.2.1.dist-info/METADATA
django_ws_scoring-0.2.1.dist-info/WHEEL
django_ws_scoring-0.2.1.dist-info/top_level.txt
django_ws_scoring-0.2.1.dist-info/RECORD
